{"fePackageDefinitions":{
    "CoreModule": {
      "package": "@openimis/fe-core",
      "git": "https://github.com/openimis/openimis-fe-core_js",
      "version": "v1.8.0"
    },
    "IndividualModule": {
      "package": "@openimis/fe-individual",
      "git": "https://github.com/openimis/openimis-fe-individual_js",
      "version": "v1.1.0"
    },
    "SocialProtectionModule": {
      "package": "@openimis/fe-social_protection",
      "git": "https://github.com/openimis/openimis-fe-social_protection_js",
      "version": "v1.2.0"
    },
    "OpenSearchReportsModule": {
      "package": "@openimis/fe-opensearch_reports",
      "git": "https://github.com/openimis/openimis-fe-opensearch_reports_js",
      "version": "v1.2.0"
    },
    "HomeModule": {
      "package": "@openimis/fe-home",
      "git": "https://github.com/openimis/openimis-fe-home_js",
      "version": "v1.5.4"
    },
    "LocationModule": {
      "package": "@openimis/fe-location",
      "git": "https://github.com/openimis/openimis-fe-location_js",
      "version": "v1.5.1"
    },
    "InsureeModule": {
      "package": "@openimis/fe-insuree",
      "git": "https://github.com/openimis/openimis-fe-insuree_js",
      "version": "v1.8.0"
    },
    "MedicalModule": {
      "package": "@openimis/fe-medical",
      "git": "https://github.com/openimis/openimis-fe-medical_js",
      "version": "v1.6.2"
    },
    "MedicalPriceListModule": {
      "package": "@openimis/fe-medical_pricelist",
      "git": "https://github.com/openimis/openimis-fe-medical_pricelist_js",
      "version": "v1.6.0"
    },
    "ProductModule": {
      "package": "@openimis/fe-product",
      "git": "https://github.com/openimis/openimis-fe-product_js",
      "version": "v1.7.0"
    },
    "PolicyModule": {
      "package": "@openimis/fe-policy",
      "git": "https://github.com/openimis/openimis-fe-policy_js",
      "version": "v1.7.0"
    },
    "PayerModule": {
      "package": "@openimis/fe-payer",
      "git": "https://github.com/openimis/openimis-fe-payer_js",
      "version": "v1.4.4"
    },
    "ContributionModule": {
      "package": "@openimis/fe-contribution",
      "git": "https://github.com/openimis/openimis-fe-contribution_js",
      "version": "v1.6.0"
    },
    "PaymentModule": {
      "package": "@openimis/fe-payment",
      "git": "https://github.com/openimis/openimis-fe-payment_js",
      "version": "v1.4.4"
    },
    "ClaimModule": {
      "package": "@openimis/fe-claim",
      "git": "https://github.com/openimis/openimis-fe-claim_js",
      "version": "v1.7.0"
    },
    "ClaimBatchModule": {
      "package": "@openimis/fe-claim_batch",
      "git": "https://github.com/openimis/openimis-fe-claim_batch_js",
      "version": "v1.4.3"
    },
    "AdminModule": {
      "package": "@openimis/fe-admin",
      "git": "https://github.com/openimis/openimis-fe-admin_js",
      "version": "v1.8.0"
    },
    "ToolsModule": {
      "package": "@openimis/fe-tools",
      "git": "https://github.com/openimis/openimis-fe-tools_js",
      "version": "v1.6.0"
    },
    "ProfileModule": {
      "package": "@openimis/fe-profile",
      "git": "https://github.com/openimis/openimis-fe-profile_js",
      "version": "v1.6.1"
    },
    "CalculationModule": {
      "package": "@openimis/fe-calculation",
      "git": "https://github.com/openimis/openimis-fe-calculation_js",
      "version": "v1.5.1"
    },
    "PolicyHolderModule": {
      "package": "@openimis/fe-policyholder",
      "git": "https://github.com/openimis/openimis-fe-policyholder_js",
      "version": "v1.6.0"
    },
    "ContributionPlanModule": {
      "package": "@openimis/fe-contribution_plan",
      "git": "https://github.com/openimis/openimis-fe-contribution_plan_js",
      "version": "v1.8.0"
    },
    "PaymentCycleModule": {
      "package": "@openimis/fe-payment_cycle",
      "git": "https://github.com/openimis/openimis-fe-payment_cycle_js",
      "version": "v1.1.0"
    },
    "ContractModule": {
      "package": "@openimis/fe-contract",
      "git": "https://github.com/openimis/openimis-fe-contract_js",
      "version": "v1.5.2"
    },
    "TasksManagementModule": {
      "package": "@openimis/fe-tasks_management",
      "git": "https://github.com/openimis/openimis-fe-tasks_management_js",
      "version": "v1.2.0"
    },
    "InvoiceModule": {
      "package": "@openimis/fe-invoice",
      "git": "https://github.com/openimis/openimis-fe-invoice_js",
      "version": "v1.7.0"
    },
    "GrievanceSocialProtectionModule": {
      "package": "@openimis/fe-grievance_social_protection",
      "git": "https://github.com/openimis/openimis-fe-grievance_social_protection_js",
      "version": "1.0.0"
    },
    "LanguageFrModule": {
      "package": "@openimis/fe-language_fr",
      "git": "https://github.com/openimis/openimis-fe-language_fr_js",
      "version": "v1.7.0"
    },
    "ClaimSamplingModule": {
      "package": "@openimis/fe-claim_sampling",
      "git": "https://github.com/openimis/openimis-fe-claim_sampling_js",
      "version": "1.0.0"
    },
    "DeduplicationModule": {
      "package": "@openimis/fe-deduplication",
      "git": "https://github.com/openimis/openimis-fe-deduplication_js",
      "version": "v1.0.1"
    },
    "PayrollModule": {
      "package": "@openimis/fe-payroll",
      "git": "https://github.com/openimis/openimis-fe-payroll_js",
      "version": "v1.2.0"
    }
  }
}