{
  "menus": [
    {
      "id": "ClientRegistryMainMenu",
      "name": "Client Registry",
      "icon": "task-icon",
      "description": "Client Registry",
         "submenus":[
            {
               "position":12,
               "id": "insuree.familiesOrGroups"
            },
            {
               "position":11,
               "id":"insuree.addFamilyOrGroup"
            },
            {
               "position":13,
               "id":"insuree.insurees"
            }
         ]
      }
  ],
  "fePackages": [
"InsureeModule"
  ],
  "bePackages": [
"insuree"
  ],
   "roles": [
    {
      "roleName": "LOCAL Administrator",
      "code": "local_admin",
      "permissions": [
        "insuree.read_insurees",
        "insuree.read_insuree",
        "insuree.read_insuree_photo",
        "insuree.insuree_officers",
        "insuree.read_insuree_family_members",
        "family.read_families",
        "insuree.insuree_policy",
        "family.create_families",
        "family.update_families",
        "family.delete_families",
        "insuree.create_insurees",
        "insuree.update_insurees",
        "insuree.delete_insurees"
      ]
    }
   ],
  "initData": [
    "../fixtures/insuree/gender.json",
    "../fixtures/insuree/education.json",
    "../fixtures/insuree/profession.json",
    "../fixtures/insuree/relations.json",
    "../fixtures/insuree/identification-types.json",
    "../fixtures/insuree/family-type.json",
    "../fixtures/insuree/relations.json",
    "../fixtures/insuree/confirmation-type.json"
  ]
}