{
  "menus": [
    {
      "mainMenu": "ClientRegistry.MainMenu",
      "position": 6,
      "id": "insuree.policyholder",
      "icon": "Business"
    }
  ],
  "fePackages": [
    "PolicyHolderModule"
  ],
  "bePackages": [
    "policyholder"
  ],
  "rights": [
    "policyholder.create_policyholder",
    "policyholder.create_policyholdercontributionplan",
    "policyholder.create_policyholderinsuree",
    "policyholder.create_policyholderinsuree_portal",
    "policyholder.create_policyholderuser",
    "policyholder.create_policyholderuser_portal",
    "policyholder.delete_policyholder",
    "policyholder.delete_policyholdercontributionplan",
    "policyholder.delete_policyholderinsuree",
    "policyholder.delete_policyholderinsuree_portal",
    "policyholder.delete_policyholderuser",
    "policyholder.delete_policyholderuser_portal",
    "policyholder.insuree_policy_portal",
    "policyholder.payment_portal",
    "policyholder.policyholder",
    "policyholder.policyholder_portal",
    "policyholder.policyholdercontributionplanbundle",
    "policyholder.policyholdercontributionplanbundle_portal",
    "policyholder.policyholderinsuree",
    "policyholder.policyholderinsuree_portal",
    "policyholder.policyholderuser",
    "policyholder.policyholderuser_portal",
    "policyholder.replace_policyholdercontributionplan",
    "policyholder.replace_policyholderinsuree",
    "policyholder.replace_policyholderinsuree_portal",
    "policyholder.replace_policyholderuser",
    "policyholder.replace_policyholderuser_portal",
    "policyholder.update_policyholder",
    "policyholder.update_policyholdercontributionplan",
    "policyholder.update_policyholderinsuree",
    "policyholder.update_policyholderinsuree_portal",
    "policyholder.update_policyholderuser",
    "policyholder.update_policyholderuser_portal"
  ]
}